sphinx_youtube_links/__init__.py
sphinx_youtube_links/_version.py
sphinx_youtube_links/common.py
sphinx_youtube_links/_static/youtube.css
sphinx_youtube_links-0.1.0.dist-info/licenses/LICENSE
sphinx_youtube_links-0.1.0.dist-info/METADATA
sphinx_youtube_links-0.1.0.dist-info/WHEEL
sphinx_youtube_links-0.1.0.dist-info/top_level.txt
sphinx_youtube_links-0.1.0.dist-info/RECORD
