Metadata-Version: 2.4
Name: sphinx-youtube-links
Version: 0.1.0
Summary: A Sphinx extension for embedding YouTube video links.
License-Expression: GPL-3.0
Requires-Python: >=3.10
License-File: LICENSE
Requires-Dist: docutils>=0.21.2
Requires-Dist: sphinx~=7.0
Requires-Dist: requests
Requires-Dist: beautifulsoup4
Dynamic: license-file
